nava/__init__.py
nava/__main__.py
nava/errors.py
nava/functions.py
nava/params.py
nava/thread.py
nava-0.8.dist-info/licenses/AUTHORS.md
nava-0.8.dist-info/licenses/LICENSE
nava-0.8.dist-info/METADATA
nava-0.8.dist-info/WHEEL
nava-0.8.dist-info/entry_points.txt
nava-0.8.dist-info/top_level.txt
nava-0.8.dist-info/RECORD
